{
  "Population" : [
    {
      "Kanton" : "Zürich",
      "2013" : 1402327,
      "2023" : 1501572,
      "2033" : 1563769
    },
    {
      "Kanton" : "Bern",
      "2013" : 986664,
      "2023" : 1012358,
      "2033" : 1019397
    },
    {
      "Kanton" : "Luzern",
      "2013" : 387451,
      "2023" : 417473,
      "2033" : 435545
    },
    {
      "Kanton" : "Uri",
      "2013" : 35730,
      "2023" : 36185,
      "2033" : 36232
    },
    {
      "Kanton" : "Schwyz",
      "2013" : 147605,
      "2023" : 154228,
      "2033" : 158961
    },
    {
      "Kanton" : "Obwalden",
      "2013" : 36592,
      "2023" : 39438,
      "2033" : 41074
    },
    {
      "Kanton" : "Nidwalden",
      "2013" : 41422,
      "2023" : 43646,
      "2033" : 44888
    },
    {
      "Kanton" : "Glarus",
      "2013" : 39147,
      "2023" : 40485,
      "2033" : 41410
    },
    {
      "Kanton" : "Zug",
      "2013" : 112569,
      "2023" : 117807,
      "2033" : 120673
    },
    {
      "Kanton" : "Freiburg",
      "2013" : 289501,
      "2023" : 317514,
      "2033" : 333457
    },
    {
      "Kanton" : "Solothurn",
      "2013" : 259267,
      "2023" : 269828,
      "2033" : 276842
    },
    {
      "Kanton" : "Basel-Stadt",
      "2013" : 193859,
      "2023" : 198352,
      "2033" : 197718
    },
    {
      "Kanton" : "Basel-Landschaft",
      "2013" : 279139,
      "2023" : 291345,
      "2033" : 298684
    },
    {
      "Kanton" : "Schaffhausen",
      "2013" : 75769,
      "2023" : 76916,
      "2033" : 77938
    },
    {
      "Kanton" : "Appenzell A.Rh.",
      "2013" : 53351,
      "2023" : 54878,
      "2033" : 56393
    },
    {
      "Kanton" : "Appenzell I.Rh.",
      "2013" : 16154,
      "2023" : 16912,
      "2033" : 17282
    },
    {
      "Kanton" : "St. Gallen",
      "2013" : 480360,
      "2023" : 500204,
      "2033" : 510330
    },
    {
      "Kanton" : "Graubünden",
      "2013" : 194024,
      "2023" : 196697,
      "2033" : 198243
    },
    {
      "Kanton" : "Aargau",
      "2013" : 629051,
      "2023" : 684897,
      "2033" : 720332
    },
    {
      "Kanton" : "Thurgau",
      "2013" : 256241,
      "2023" : 275867,
      "2033" : 285685
    },
    {
      "Kanton" : "Tessin",
      "2013" : 345787,
      "2023" : 358320,
      "2033" : 364590
    },
    {
      "Kanton" : "Waadt",
      "2013" : 748085,
      "2023" : 826678,
      "2033" : 875087
    },
    {
      "Kanton" : "Wallis",
      "2013" : 318757,
      "2023" : 334946,
      "2033" : 342577
    },
    {
      "Kanton" : "Neuenburg",
      "2013" : 172356,
      "2023" : 174881,
      "2033" : 176381
    },
    {
      "Kanton" : "Genf",
      "2013" : 475705,
      "2023" : 511178,
      "2033" : 536849
    },
    {
      "Kanton" : "Jura",
      "2013" : 70646,
      "2023" : 72022,
      "2033" : 72072
    }
  ]
}